{
    "notices": [
        {
            "id": 1,
            "name": "이개발",
            "rank": "대리",
            "team": "개발팀",
            "date": "10월 20일 14:40"
        },
        {
            "id": 2,
            "name": "나경호",
            "rank": "사원",
            "team": "보안팀",
            "date": "10월 20일 12:30"
        },
        {
            "id": 3,
            "name": "최디자인",
            "rank": "팀장",
            "team": "디자인팀",
            "date": "10월 20일 8:59"
        },
        {
            "id": 4,
            "name": "송인사",
            "rank": "사원",
            "team": "인사팀",
            "date": "10월 19일 17:40"
        },
        {
            "id": 5,
            "name": "차마케팅",
            "rank": "부장",
            "team": "마케팅팀",
            "date": "10월 19일 13:33"
        }
    ]
}